second_opinion/__init__.py
second_opinion-2.2.0.dist-info/METADATA
second_opinion-2.2.0.dist-info/WHEEL
second_opinion-2.2.0.dist-info/entry_points.txt
second_opinion-2.2.0.dist-info/licenses/LICENSE
second_opinion-2.2.0.dist-info/RECORD
