Metadata-Version: 2.3
Name: second_opinion
Version: 2.2.0
Summary: Generates AI Code Reviews
Project-URL: Homepage, https://github.com/wayneplural/second-opinion
Project-URL: Issues, https://github.com/wayneplural/second-opinion/issues
Author-email: Wayne Bratley <wayne@plural.ai>
License-File: LICENSE
Classifier: License :: OSI Approved :: MIT License
Classifier: Operating System :: OS Independent
Classifier: Programming Language :: Python :: 3
Requires-Python: >=3.8
Requires-Dist: openai>=1.35.13
